README.md
setup.py
dotman/__init__.py
dotman.egg-info/PKG-INFO
dotman.egg-info/SOURCES.txt
dotman.egg-info/dependency_links.txt
dotman.egg-info/top_level.txt
scripts/dotman