Metadata-Version: 1.1
Name: dotman
Version: 1.1.0
Summary: Manage your dotfiles easily.
Home-page: http://github.com/xmonader/dotman
Author: Ahmed T. Youssef
Author-email: xmonader@gmail.com
License: BSD 3-Clause License
Platform: UNKNOWN
Classifier: Development Status :: 4 - Beta
Classifier: Environment :: Console
Classifier: Intended Audience :: Developers
Classifier: License :: OSI Approved :: BSD License
Classifier: Operating System :: OS Independent
Classifier: Programming Language :: Python
